[{  
   "HotelListResponse":{  
      "customerSessionId":"0ABAAA3A-8A10-4914-9862-917509901424",
      "numberOfRoomsRequested":1,
      "moreResultsAvailable":true,
      "cacheKey":"-19c8a104:14986917509:-141a",
      "cacheLocation":"10.186.170.58:7300",
      "cachedSupplierResponse":{  
         "@supplierCacheTolerance":"NOT_SUPPORTED",
         "@cachedTime":"0",
         "@supplierRequestNum":"225",
         "@supplierResponseNum":"1",
         "@supplierResponseTime":"230",
         "@candidatePreptime":"4",
         "@otherOverheadTime":"16",
         "@tpidUsed":"5001",
         "@matchedCurrency":"true",
         "@matchedLocale":"true"
      },
      "HotelList":{  
         "@size":"1",
         "@activePropertyCount":"245",
         "HotelSummary":{  
            "@order":"0",
            "@ubsScore":"343108576",
            "hotelId":148505,
            "name":"Mayflower Park Hotel",
            "address1":"405 Olive Way",
            "city":"Seattle",
            "stateProvinceCode":"WA",
            "postalCode":98101,
            "countryCode":"US",
            "airportCode":"SEA",
            "supplierType":"E",
            "propertyCategory":1,
            "hotelRating":3.5,
            "confidenceRating":85,
            "amenityMask":3,
            "tripAdvisorRating":4.5,
            "tripAdvisorReviewCount":1355,
            "tripAdvisorRatingUrl":"http://www.tripadvisor.com/img/cdsi/img2/ratings/traveler/4.5-39958-4.png",
            "locationDescription":"Near Pike Place Market",
            "shortDescription":"&lt;p&gt;&lt;b&gt;Property Location&lt;/b&gt; &lt;br /&gt;With a stay at Mayflower Park Hotel, you&apos;ll be centrally located in Seattle, steps from Westlake Center and minutes from Pike Place Market. This historic hotel is",
            "highRate":309,
            "lowRate":309,
            "rateCurrencyCode":"USD",
            "latitude":47.61223,
            "longitude":-122.33853,
            "proximityDistance":11.359455,
            "proximityUnit":"MI",
            "hotelInDestination":true,
            "thumbNailUrl":"/hotels/1000000/30000/26900/26893/26893_43_t.jpg",
            "deepLink":"http://www.travelnow.com/templates/55505/hotels/148505/overview?lang=en&amp;currency=USD&amp;standardCheckin=09/04/2015&amp;standardCheckout=09/05/2015&amp;roomsCount=1&amp;rooms[0].adultsCount=2",
            "RoomRateDetailsList":{  
               "RoomRateDetails":{  
                  "roomTypeCode":9955,
                  "rateCode":9955,
                  "maxRoomOccupancy":2,
                  "quotedRoomOccupancy":2,
                  "minGuestAge":0,
                  "roomDescription":"Classic Room, 1 Queen Bed",
                  "propertyAvailable":true,
                  "propertyRestricted":false,
                  "expediaPropertyId":26893,
                  "RateInfos":{  
                     "@size":"1",
                     "RateInfo":{  
                        "@priceBreakdown":"true",
                        "@promo":"false",
                        "@rateChange":"false",
                        "RoomGroup":{  
                           "Room":{  
                              "numberOfAdults":2,
                              "numberOfChildren":0
                           }
                        },
                        "ChargeableRateInfo":{  
                           "@averageBaseRate":"309.0",
                           "@averageRate":"309.0",
                           "@commissionableUsdTotal":"309.0",
                           "@currencyCode":"USD",
                           "@maxNightlyRate":"309.0",
                           "@nightlyRateTotal":"309.0",
                           "@grossProfitOffline":"59.55",
                           "@grossProfitOnline":"84.13",
                           "@surchargeTotal":"55.15",
                           "@total":"364.15",
                           "NightlyRatesPerRoom":{  
                              "@size":"1",
                              "NightlyRate":{  
                                 "@baseRate":"309.0",
                                 "@rate":"309.0",
                                 "@promo":"false"
                              }
                           },
                           "Surcharges":{  
                              "@size":"1",
                              "Surcharge":{  
                                 "@type":"TaxAndServiceFee",
                                 "@amount":"55.15"
                              }
                           }
                        },
                        "nonRefundable":false,
                        "rateType":"MerchantStandard",
                        "currentAllotment":17
                     }
                  },
                  "ValueAdds":{  
                     "@size":"1",
                     "ValueAdd":{  
                        "description":"Free Wireless Internet"
                     }
                  }
               }
            }
         }
      }
   }
},
{  
   "HotelListResponse":{  
      "customerSessionId":"0ABAAA3A-8A10-4914-9862-917509901424",
      "numberOfRoomsRequested":1,
      "moreResultsAvailable":true,
      "cacheKey":"-19c8a104:14986917509:-141a",
      "cacheLocation":"10.186.170.58:7300",
      "cachedSupplierResponse":{  
         "@supplierCacheTolerance":"NOT_SUPPORTED",
         "@cachedTime":"0",
         "@supplierRequestNum":"225",
         "@supplierResponseNum":"1",
         "@supplierResponseTime":"230",
         "@candidatePreptime":"4",
         "@otherOverheadTime":"16",
         "@tpidUsed":"5001",
         "@matchedCurrency":"true",
         "@matchedLocale":"true"
      },
      "HotelList":{  
         "@size":"1",
         "@activePropertyCount":"245",
         "HotelSummary":{  
            "@order":"0",
            "@ubsScore":"343108576",
            "hotelId":148505,
            "name":"Mayflower Park Hotel",
            "address1":"405 Olive Way",
            "city":"Seattle",
            "stateProvinceCode":"WA",
            "postalCode":98101,
            "countryCode":"US",
            "airportCode":"SEA",
            "supplierType":"E",
            "propertyCategory":1,
            "hotelRating":3.5,
            "confidenceRating":85,
            "amenityMask":3,
            "tripAdvisorRating":4.5,
            "tripAdvisorReviewCount":1355,
            "tripAdvisorRatingUrl":"http://www.tripadvisor.com/img/cdsi/img2/ratings/traveler/4.5-39958-4.png",
            "locationDescription":"Near Pike Place Market",
            "shortDescription":"&lt;p&gt;&lt;b&gt;Property Location&lt;/b&gt; &lt;br /&gt;With a stay at Mayflower Park Hotel, you&apos;ll be centrally located in Seattle, steps from Westlake Center and minutes from Pike Place Market. This historic hotel is",
            "highRate":309,
            "lowRate":309,
            "rateCurrencyCode":"USD",
            "latitude":47.61223,
            "longitude":-122.33853,
            "proximityDistance":11.359455,
            "proximityUnit":"MI",
            "hotelInDestination":true,
            "thumbNailUrl":"/hotels/1000000/30000/26900/26893/26893_43_t.jpg",
            "deepLink":"http://www.travelnow.com/templates/55505/hotels/148505/overview?lang=en&amp;currency=USD&amp;standardCheckin=09/04/2015&amp;standardCheckout=09/05/2015&amp;roomsCount=1&amp;rooms[0].adultsCount=2",
            "RoomRateDetailsList":{  
               "RoomRateDetails":{  
                  "roomTypeCode":9955,
                  "rateCode":9955,
                  "maxRoomOccupancy":2,
                  "quotedRoomOccupancy":2,
                  "minGuestAge":0,
                  "roomDescription":"Classic Room, 1 Queen Bed",
                  "propertyAvailable":true,
                  "propertyRestricted":false,
                  "expediaPropertyId":26893,
                  "RateInfos":{  
                     "@size":"1",
                     "RateInfo":{  
                        "@priceBreakdown":"true",
                        "@promo":"false",
                        "@rateChange":"false",
                        "RoomGroup":{  
                           "Room":{  
                              "numberOfAdults":2,
                              "numberOfChildren":0
                           }
                        },
                        "ChargeableRateInfo":{  
                           "@averageBaseRate":"309.0",
                           "@averageRate":"309.0",
                           "@commissionableUsdTotal":"309.0",
                           "@currencyCode":"USD",
                           "@maxNightlyRate":"309.0",
                           "@nightlyRateTotal":"309.0",
                           "@grossProfitOffline":"59.55",
                           "@grossProfitOnline":"84.13",
                           "@surchargeTotal":"55.15",
                           "@total":"364.15",
                           "NightlyRatesPerRoom":{  
                              "@size":"1",
                              "NightlyRate":{  
                                 "@baseRate":"309.0",
                                 "@rate":"309.0",
                                 "@promo":"false"
                              }
                           },
                           "Surcharges":{  
                              "@size":"1",
                              "Surcharge":{  
                                 "@type":"TaxAndServiceFee",
                                 "@amount":"55.15"
                              }
                           }
                        },
                        "nonRefundable":false,
                        "rateType":"MerchantStandard",
                        "currentAllotment":17
                     }
                  },
                  "ValueAdds":{  
                     "@size":"1",
                     "ValueAdd":{  
                        "description":"Free Wireless Internet"
                     }
                  }
               }
            }
         }
      }
   }
}]